adbtool/__init__.py
adbtool/adbtool.py
adbtool/cmd.py
adbtool/config.py
adbtool/errors.py
adbtool/subcommands/__init__.py
adbtool/subcommands/adbdevice.py
adbtool/subcommands/adbpull.py
adbtool/subcommands/adbpush.py
adbtool/subcommands/apkinfo.py
adbtool/subcommands/apkinstall.py
adbtool/subcommands/apksigner.py
adbtool/subcommands/apkuninstall.py
adbtool/subcommands/assetbundleinfo.py
adbtool/subcommands/asshader.py
adbtool/subcommands/il2cpp.py
adbtool/subcommands/malioc.py
adbtool/subcommands/pagesize.py
adbtool/subcommands/procfd.py
adbtool-0.0.27.dist-info/METADATA
adbtool-0.0.27.dist-info/WHEEL
adbtool-0.0.27.dist-info/entry_points.txt
adbtool-0.0.27.dist-info/licenses/LICENSE
adbtool-0.0.27.dist-info/RECORD
