Metadata-Version: 2.4
Name: adbtool
Version: 0.0.27
Summary: A friendly android adb command-line tool
Project-URL: Homepage, http://github.com/litefeel/pycommon
Project-URL: Repository, http://github.com/litefeel/pycommon.git
Project-URL: Bug Tracker, http://github.com/litefeel/pycommon/issues
Author-email: litefeel <litefeel@gmail.com>
License: MIT License
License-File: LICENSE
Keywords: Android,adb
Classifier: Development Status :: 4 - Beta
Classifier: Programming Language :: Python
Classifier: Topic :: Software Development :: Libraries :: Python Modules
Requires-Python: >=3.10
Requires-Dist: litefeel-pycommon>=0.4.15
Requires-Dist: pyyaml
Requires-Dist: semantic-version
Requires-Dist: var-dump
